music_brainz_api_micro/__init__.py
music_brainz_api_micro/cover_reponse.py
music_brainz_api_micro/music_brainz_api.py
music_brainz_api_micro-0.1.10.dist-info/METADATA
music_brainz_api_micro-0.1.10.dist-info/WHEEL
music_brainz_api_micro-0.1.10.dist-info/licenses/LICENSE
music_brainz_api_micro-0.1.10.dist-info/RECORD
