Metadata-Version: 2.4
Name: music_brainz_api_micro
Version: 0.1.10
Summary: A micro client for MusicBrainz, implements simple functions to retrieve information
Author: Samuel Shiels
License-File: LICENSE
Classifier: Development Status :: 3 - Alpha
Classifier: Environment :: Other Environment
Classifier: Intended Audience :: Developers
Classifier: Intended Audience :: System Administrators
Classifier: License :: OSI Approved :: MIT License
Classifier: Operating System :: POSIX :: Linux
Classifier: Programming Language :: Python :: 3
Classifier: Topic :: Utilities
Requires-Python: >=3.11.5
Requires-Dist: jsonpickle
Requires-Dist: rest-client-micro
